odoo/addons/document_quick_access/README.rst
odoo/addons/document_quick_access/__init__.py
odoo/addons/document_quick_access/__manifest__.py
odoo/addons/document_quick_access/i18n/document_quick_access.pot
odoo/addons/document_quick_access/i18n/es.po
odoo/addons/document_quick_access/models/__init__.py
odoo/addons/document_quick_access/models/base.py
odoo/addons/document_quick_access/models/document_quick_access_rule.py
odoo/addons/document_quick_access/readme/CONFIGURE.rst
odoo/addons/document_quick_access/readme/CONTRIBUTORS.rst
odoo/addons/document_quick_access/readme/DESCRIPTION.rst
odoo/addons/document_quick_access/readme/ROADMAP.rst
odoo/addons/document_quick_access/readme/USAGE.rst
odoo/addons/document_quick_access/security/ir.model.access.csv
odoo/addons/document_quick_access/static/description/icon.png
odoo/addons/document_quick_access/static/description/index.html
odoo/addons/document_quick_access/static/src/js/document_quick_access_launcher.js
odoo/addons/document_quick_access/static/src/xml/document_quick_access_launcher.xml
odoo/addons/document_quick_access/tests/__init__.py
odoo/addons/document_quick_access/tests/test_document_quick_access.py
odoo/addons/document_quick_access/views/assets_backend.xml
odoo/addons/document_quick_access/views/document_quick_access_rule.xml
odoo13_addon_document_quick_access-13.0.1.0.1.dev9.dist-info/METADATA
odoo13_addon_document_quick_access-13.0.1.0.1.dev9.dist-info/WHEEL
odoo13_addon_document_quick_access-13.0.1.0.1.dev9.dist-info/top_level.txt
odoo13_addon_document_quick_access-13.0.1.0.1.dev9.dist-info/RECORD
